adscan_wrapper/__init__.py
adscan_wrapper/launcher.py
adscan_wrapper/adscan_bundle/adscan-cli
adscan-555.555.559.dist-info/METADATA
adscan-555.555.559.dist-info/WHEEL
adscan-555.555.559.dist-info/entry_points.txt
adscan-555.555.559.dist-info/top_level.txt
adscan-555.555.559.dist-info/RECORD
