Metadata-Version: 2.4
Name: adscan
Version: 555.555.559
Summary: A PyPI wrapper for the ADScan-CLI binary.
Author: ADscan
Project-URL: homepage, https://github.com/ADscanPro/adscan
Classifier: Programming Language :: Python :: 3
Classifier: Operating System :: POSIX :: Linux
Requires-Python: >=3.9
